README.rst
setup.cfg
setup.py
sci/__init__.py
sci/_units.py
sci/cli.py
sci/definitions.py
sci/driver.py
sci/errors.py
sci/instruments.py
sci/protocols.py
sci/refs.py
sci/utils.py
scici.egg-info/PKG-INFO
scici.egg-info/SOURCES.txt
scici.egg-info/dependency_links.txt
scici.egg-info/top_level.txt
tests/__init__.py
tests/test_instruments.py
tests/test_refs.py