Metadata-Version: 1.2
Name: scici
Version: 0.1.0
Summary: design, automate and share any lab experiment
Home-page: https://github.com/scici/sci
Author: scici
Author-email: sci@sci.ci
License: UNKNOWN
Platform: UNKNOWN
Classifier: Development Status :: 2 - Pre-Alpha
Classifier: Programming Language :: Python
Classifier: Programming Language :: Python :: 3.5
Classifier: Programming Language :: Python :: 3.6
Requires-Python: >= 3.6
